Metadata-Version: 2.1
Name: addcomments
Version: 0.0.3
Summary: add database table column comments
Home-page: https://github.com/codeliuyang/django_mysql_comment
Author: yangliu
Author-email: codeliuyang@163.com
License: UNKNOWN
Platform: UNKNOWN
Classifier: Programming Language :: Python :: 3
Classifier: License :: OSI Approved :: MIT License
Classifier: Operating System :: OS Independent
Requires-Python: >=3.6
